fusesoc/nexys4ddr_nodemcu/rtl/verilog/spi_slave.v
`timescale 1ns / 1ps
//////////////////////////////////////////////////////////////////////////////////
// Company: 
// Engineer: 
// 
// Create Date: 11.02.2018 18:28:54
// Design Name: 
// Module Name: SPI_slave
// Project Name: 
// Target Devices: 
// Tool Versions: 
// Description: 
// 
// Dependencies: 
// 
// Revision:
// Revision 0.01 - File Created
// Additional Comments:
// 
//////////////////////////////////////////////////////////////////////////////////
/* Simple SPI slave code from http://www.fpga4fun.com/SPI2.html */
/*SPI MODE 0*/

module SPI_slave(clk, SCK, MOSI, MISO, SSEL, LED, byte_received, byte_data_received);
input clk;

input SCK, SSEL, MOSI;
output MISO;

output LED;
output reg [7:0] byte_data_received;
output reg byte_received;

// sync SCK to the FPGA clock using a 3-bits shift register
reg [2:0] SCKr;  always @(posedge clk) SCKr <= {SCKr[1:0], SCK};
wire SCK_risingedge = (SCKr[2:1]==2'b01);  // now we can detect SCK rising edges
wire SCK_fallingedge = (SCKr[2:1]==2'b10);  // and falling edges

// same thing for SSEL
reg [2:0] SSELr;  always @(posedge clk) SSELr <= {SSELr[1:0], SSEL};
wire SSEL_active = ~SSELr[1];  // SSEL is active low
wire SSEL_startmessage = (SSELr[2:1]==2'b10);  // message starts at falling edge
wire SSEL_endmessage = (SSELr[2:1]==2'b01);  // message stops at rising edge

// and for MOSI
reg [1:0] MOSIr;  always @(posedge clk) MOSIr <= {MOSIr[0], MOSI};
wire MOSI_data = MOSIr[1];


// we handle SPI in 8-bits format, so we need a 3 bits counter to count the bits as they come in
reg [2:0] bitcnt;

//reg byte_received;  // high when a byte has been received
//reg [7:0] byte_data_received;

always @(posedge clk)
begin
  if(~SSEL_active)
    bitcnt <= 3'b000;
  else
  if(SCK_risingedge)
  begin
    bitcnt <= bitcnt + 3'b001;

    // implement a shift-left register (since we receive the data MSB first)
    byte_data_received <= {byte_data_received[6:0], MOSI_data};
  end
end

always @(posedge clk) byte_received <= SSEL_active && SCK_risingedge && (bitcnt==3'b111);

// we use the LSB of the data received to control an LED
reg LED;
always @(posedge clk) if(byte_received) LED <= byte_data_received[0];


reg [7:0] byte_data_sent;

reg [7:0] cnt;
always @(posedge clk) if(SSEL_startmessage) cnt<=cnt+8'h1;  // count the messages

always @(posedge clk)
if(SSEL_active)
begin
  if(SSEL_startmessage)
    byte_data_sent <= cnt;  // first byte sent in a message is the message count
  else
  if(SCK_fallingedge)
  begin
    if(bitcnt==3'b000)
      byte_data_sent <= 8'h00;  // after that, we send 0s
    else
      byte_data_sent <= {byte_data_sent[6:0], 1'b0};
  end
end

assign MISO = byte_data_sent[7];  // send MSB first
// we assume that there is only one slave on the SPI bus
// so we don't bother with a tri-state buffer for MISO
// otherwise we would need to tri-state MISO when SSEL is inactive

endmodule

fusesoc/nexys4ddr_nodemcu/test/SPI_slave_test/dump.vcd
$date
	Wed Feb 21 14:33:30 2018
$end
$version
	Icarus Verilog
$end
$timescale
	1ps
$end
$scope module SPI_slave $end
$var wire 1 ! MOSI $end
$var wire 1 " SCK $end
$var wire 1 # SSEL $end
$var wire 1 $ SSEL_active $end
$var wire 1 % clk $end
$var wire 1 & SSEL_startmessage $end
$var wire 1 ' SSEL_endmessage $end
$var wire 1 ( SCK_risingedge $end
$var wire 1 ) SCK_fallingedge $end
$var wire 1 * MOSI_data $end
$var wire 1 + MISO $end
$var reg 1 , LED $end
$var reg 2 - MOSIr [1:0] $end
$var reg 3 . SCKr [2:0] $end
$var reg 3 / SSELr [2:0] $end
$var reg 3 0 bitcnt [2:0] $end
$var reg 8 1 byte_data_received [7:0] $end
$var reg 8 2 byte_data_sent [7:0] $end
$var reg 1 3 byte_received $end
$var reg 8 4 cnt [7:0] $end
$upscope $end
$enddefinitions $end
#0
$dumpvars
bx 4
x3
bx 2
bx 1
bx 0
bx0 /
bx0 .
bx1 -
x,
x+
x*
x)
x(
x'
x&
1%
x$
0#
0"
1!
$end
#5
0%
#10
1$
1*
0'
0(
b11 -
bx00 /
bx00 .
1%
#15
0%
#20
0)
0&
b0 .
b0 /
03
1%
#25
0%
#30
1%
#35
0%
#40
1%
#45
0%
#50
1%
#55
0%
#60
1%
#65
0%
#70
1%
#75
0%
#80
1%
#85
0%
#90
1%
#95
0%
#100
b1 .
1%
1"
#105
0%
#110
1(
b11 .
1%
#115
0%
#120
0(
b111 .
bx1 1
x3
1%
#125
0%
#130
03
1%
#135
0%
#140
1%
#145
0%
#150
1%
#155
0%
#160
1%
#165
0%
#170
1%
#175
0%
#180
1%
#185
0%
#190
1%
#195
0%
#200
b110 .
1%
0"
#205
0%
#210
1)
b100 .
1%
#215
0%
#220
0)
b0 .
bx0 2
1%
#225
0%
#230
1%
#235
0%
#240
1%
#245
0%
#250
1%
#255
0%
#260
1%
#265
0%
#270
1%
#275
0%
#280
1%
#285
0%
#290
1%
#295
0%
#300
b1 .
1%
1"
#305
0%
#310
1(
b11 .
1%
#315
0%
#320
0(
b111 .
bx11 1
x3
1%
#325
0%
#330
03
1%
#335
0%
#340
1%
#345
0%
#350
1%
#355
0%
#360
1%
#365
0%
#370
1%
#375
0%
#380
1%
#385
0%
#390
1%
#395
0%
#400
b110 .
1%
0"
#405
0%
#410
1)
b100 .
1%
#415
0%
#420
0)
b0 .
bx00 2
1%
#425
0%
#430
1%
#435
0%
#440
1%
#445
0%
#450
1%
#455
0%
#460
1%
#465
0%
#470
1%
#475
0%
#480
1%
#485
0%
#490
1%
#495
0%
#500
b1 .
1%
1"
#505
0%
#510
1(
b11 .
1%
#515
0%
#520
0(
b111 .
bx111 1
x3
1%
#525
0%
#530
03
1%
#535
0%
#540
1%
#545
0%
#550
1%
#555
0%
#560
1%
#565
0%
#570
1%
#575
0%
#580
1%
#585
0%
#590
1%
#595
0%
#600
b110 .
1%
0"
#605
0%
#610
1)
b100 .
1%
#615
0%
#620
0)
b0 .
bx000 2
1%
#625
0%
#630
1%
#635
0%
#640
1%
#645
0%
#650
1%
#655
0%
#660
1%
#665
0%
#670
1%
#675
0%
#680
1%
#685
0%
#690
1%
#695
0%
#700
b1 .
1%
1"
#705
0%
#710
1(
b11 .
1%
#715
0%
#720
0(
b111 .
bx1111 1
x3
1%
#725
0%
#730
03
1%
#735
0%
#740
1%
#745
0%
#750
1%
#755
0%
#760
1%
#765
0%
#770
1%
#775
0%
#780
1%
#785
0%
#790
1%
#795
0%
#800
b110 .
1%
0"
#805
0%
#810
1)
b100 .
1%
#815
0%
#820
0)
b0 .
bx0000 2
1%
#825
0%
#830
1%
#835
0%
#840
1%
#845
0%
#850
1%
#855
0%
#860
1%
#865
0%
#870
1%
#875
0%
#880
1%
#885
0%
#890
1%
#895
0%
#900
b1 .
1%
1"
#905
0%
#910
1(
b11 .
1%
#915
0%
#920
0(
b111 .
bx11111 1
x3
1%
#925
0%
#930
03
1%
#935
0%
#940
1%
#945
0%
#950
1%
#955
0%
#960
1%
#965
0%
#970
1%
#975
0%
#980
1%
#985
0%
#990
1%
#995
0%
#1000
b110 .
b10 -
1%
0!
0"
#1005
0%
#1010
0*
1)
b0 -
b100 .
1%
#1015
0%
#1020
0)
b0 .
bx00000 2
1%
#1025
0%
#1030
1%
#1035
0%
#1040
1%
#1045
0%
#1050
1%
#1055
0%
#1060
1%
#1065
0%
#1070
1%
#1075
0%
#1080
1%
#1085
0%
#1090
1%
#1095
0%
#1100
b1 .
1%
1"
#1105
0%
#1110
1(
b11 .
1%
#1115
0%
#1120
0(
b111 .
bx111110 1
x3
1%
#1125
0%
#1130
03
1%
#1135
0%
#1140
1%
#1145
0%
#1150
1%
#1155
0%
#1160
1%
#1165
0%
#1170
1%
#1175
0%
#1180
1%
#1185
0%
#1190
1%
#1195
0%
#1200
b110 .
b1 -
1%
1!
0"
#1205
0%
#1210
1*
1)
b11 -
b100 .
1%
#1215
0%
#1220
0)
b0 .
bx000000 2
1%
#1225
0%
#1230
1%
#1235
0%
#1240
1%
#1245
0%
#1250
1%
#1255
0%
#1260
1%
#1265
0%
#1270
1%
#1275
0%
#1280
1%
#1285
0%
#1290
1%
#1295
0%
#1300
b1 .
1%
1"
#1305
0%
#1310
1(
b11 .
1%
#1315
0%
#1320
0(
b111 .
bx1111101 1
x3
1%
#1325
0%
#1330
03
1%
#1335
0%
#1340
1%
#1345
0%
#1350
1%
#1355
0%
#1360
1%
#1365
0%
#1370
1%
#1375
0%
#1380
1%
#1385
0%
#1390
1%
#1395
0%
#1400
b110 .
b10 -
1%
0!
0"
#1405
0%
#1410
0*
1)
b0 -
b100 .
1%
#1415
0%
#1420
0)
b0 .
bx0000000 2
1%
#1425
0%
#1430
1%
#1435
0%
#1440
1%
#1445
0%
#1450
1%
#1455
0%
#1460
1%
#1465
0%
#1470
1%
#1475
0%
#1480
1%
#1485
0%
#1490
1%
#1495
0%
#1500
b1 .
1%
1"
#1505
0%
#1510
1(
b11 .
1%
#1515
0%
#1520
0(
b111 .
b11111010 1
x3
1%
#1525
0%
#1530
03
1%
